aishalib/aishalib.py
aishalib/llmbackend.py
aishalib/memory.py
aishalib/tools.py
aishalib/utils.py
aishalib-0.0.25.dist-info/LICENSE
aishalib-0.0.25.dist-info/METADATA
aishalib-0.0.25.dist-info/WHEEL
aishalib-0.0.25.dist-info/top_level.txt
aishalib-0.0.25.dist-info/RECORD
