Metadata-Version: 2.1
Name: aishalib
Version: 0.0.25
Summary: AI Smart Human Assistant Library
Author-email: Vladimir Petrukhin <man4j@ya.ru>
Project-URL: Homepage, https://github.com/Equiron-AI/aishalib
Classifier: Development Status :: 4 - Beta
Classifier: Programming Language :: Python :: 3.10
Classifier: Programming Language :: Python :: 3.11
Classifier: License :: OSI Approved :: MIT License
Classifier: Operating System :: OS Independent
Requires-Python: >=3.10
License-File: LICENSE
Requires-Dist: transformers >=4.44.0
Requires-Dist: jinja2 >=3.1.4
Requires-Dist: sseclient-py
Requires-Dist: pytz
